synthetic_aia_mia/__init__.py
synthetic_aia_mia/remove_cache.sh
synthetic_aia_mia/aia/__init__.py
synthetic_aia_mia/aia/rf.py
synthetic_aia_mia/aia/soft.py
synthetic_aia_mia/experiments/__init__.py
synthetic_aia_mia/experiments/__main__.py
synthetic_aia_mia/experiments/adult.py
synthetic_aia_mia/experiments/adult_mia.py
synthetic_aia_mia/experiments/utk.py
synthetic_aia_mia/experiments/utk_mia.py
synthetic_aia_mia/fetch_data/__init__.py
synthetic_aia_mia/fetch_data/adult.py
synthetic_aia_mia/fetch_data/split.py
synthetic_aia_mia/fetch_data/utk.py
synthetic_aia_mia/generator/__init__.py
synthetic_aia_mia/generator/adult.py
synthetic_aia_mia/generator/example.py
synthetic_aia_mia/generator/utk
synthetic_aia_mia/generator/utk.py
synthetic_aia_mia/metrics/__init__.py
synthetic_aia_mia/mia/__init__.py
synthetic_aia_mia/mia/ml.py
synthetic_aia_mia/mia/rf.py
synthetic_aia_mia/mia_synthetic/__init__.py
synthetic_aia_mia/mia_synthetic/adult.py
synthetic_aia_mia/mia_synthetic/utk.py
synthetic_aia_mia/predictor/__init__.py
synthetic_aia_mia/predictor/adult.py
synthetic_aia_mia/predictor/utk.py
synthetic_aia_mia-0.0.45.dist-info/METADATA
synthetic_aia_mia-0.0.45.dist-info/WHEEL
synthetic_aia_mia-0.0.45.dist-info/RECORD
