Metadata-Version: 2.3
Name: synthetic_aia_mia
Version: 0.0.45
Summary: AIA and MIA attack versus synthetic and real data.
Project-URL: Homepage, https://gitlab.inria.fr/jaalmoes/synthetic
Project-URL: Bug Tracker, https://gitlab.inria.fr/jaalmoes/synthetic
Author-email: Jan Aalmoes <jan.aalmoes@protonmail.com>, Thomas Lebrun <thomas.lebrun@inria.fr>
Classifier: License :: OSI Approved :: GNU General Public License v3 or later (GPLv3+)
Classifier: Operating System :: OS Independent
Classifier: Programming Language :: Python :: 3
Requires-Python: >=3.7
Requires-Dist: aia-fairness
Requires-Dist: finit-classifier
Requires-Dist: hyperopt
Requires-Dist: numpy
Requires-Dist: opencv-python
Requires-Dist: pandas
Requires-Dist: pygan
Requires-Dist: ray
Requires-Dist: ray[data]
Requires-Dist: ray[serve]
Requires-Dist: ray[train]
Requires-Dist: ray[tune]
Requires-Dist: sdv
